README.rst
setup.py
bin/rps
webs/__init__.py
webs/rps.py
webs.egg-info/PKG-INFO
webs.egg-info/SOURCES.txt
webs.egg-info/dependency_links.txt
webs.egg-info/pbr.json
webs.egg-info/top_level.txt