Metadata-Version: 1.1
Name: webs
Version: 0.0.4
Summary: Web Scraping Tools
Home-page: http://github.com/lorien/webs
Author: Gregory Petukhov
Author-email: lorien@lorien.name
License: MIT
Keywords: script web scraping console
Platform: UNKNOWN
Classifier: Programming Language :: Python
Classifier: Programming Language :: Python :: 2.6
Classifier: Programming Language :: Python :: 2.7
Classifier: Programming Language :: Python :: 3.3
Classifier: Programming Language :: Python :: 3.4
Classifier: License :: OSI Approved :: MIT License
Classifier: Development Status :: 5 - Production/Stable
Classifier: Environment :: Console
Classifier: Intended Audience :: Developers
Classifier: Operating System :: OS Independent
Classifier: Topic :: Software Development :: Libraries :: Python Modules
Classifier: Topic :: Utilities
